run_sql_job/__init__.py
run_sql_job/main.py
run_sql_job-1.0.0.data/scripts/run-sql-job
run_sql_job-1.0.0.dist-info/METADATA
run_sql_job-1.0.0.dist-info/WHEEL
run_sql_job-1.0.0.dist-info/top_level.txt
run_sql_job-1.0.0.dist-info/RECORD
