Metadata-Version: 2.1
Name: run-sql-job
Version: 1.0.0
Summary: Job that run sql script
Home-page: https://github.com/mantis-software-company/rabbitmq2psql-as-json
Author: Derya Pelin Deniz
Author-email: info@mantis.com.tr
License: UNKNOWN
Platform: all
Classifier: License :: OSI Approved :: Apache Software License
Classifier: Topic :: Internet
Classifier: Topic :: Software Development
Classifier: Programming Language :: Python :: 3.8
Requires-Python: >3.8.*, <4
Requires-Dist: psycopg2-binary
